<?xml version="1.0" encoding="utf-8"?>                                                                                                                                                                                                                         
<edmx:Edmx Version="4.0" xmlns:edmx="http://docs.oasis-open.org/odata/ns/edmx">                                                                                                                                                                                
    <edmx:Reference Uri="../../catalogservice;v=2/Vocabularies(TechnicalName='%2FIWBEP%2FVOC_COMMON',Version='0001',SAP__Origin='LOCAL')/$value">                                                                                                              
        <edmx:Include Namespace="com.sap.vocabularies.Common.v1" Alias="Common"/>                                                                                                                                                                              
    </edmx:Reference>                                                                                                                                                                                                                                          
    <edmx:Reference Uri="../../catalogservice;v=2/Vocabularies(TechnicalName='%2FIWBEP%2FVOC_UI',Version='0001',SAP__Origin='LOCAL')/$value">                                                                                                                  
        <edmx:Include Namespace="com.sap.vocabularies.UI.v1" Alias="UI"/>                                                                                                                                                                                      
    </edmx:Reference>                                                                                                                                                                                                                                          
    <edmx:Reference Uri="../../catalogservice;v=2/Vocabularies(TechnicalName='%2FIWBEP%2FVOC_COMMUNICATION',Version='0001',SAP__Origin='LOCAL')/$value">                                                                                                       
        <edmx:Include Namespace="com.sap.vocabularies.Communication.v1" Alias="Communication"/>                                                                                                                                                                
    </edmx:Reference>                                                                                                                                                                                                                                          
    <edmx:Reference Uri="../../catalogservice;v=2/Vocabularies(TechnicalName='%2FIWBEP%2FVOC_PERSONALDATA',Version='0001',SAP__Origin='LOCAL')/$value">                                                                                                        
        <edmx:Include Namespace="com.sap.vocabularies.PersonalData.v1" Alias="PersonalData"/>                                                                                                                                                                  
    </edmx:Reference>                                                                                                                                                                                                                                          
    <edmx:Reference Uri="../../catalogservice;v=2/Vocabularies(TechnicalName='%2FIWBEP%2FVOC_VALIDATION',Version='0001',SAP__Origin='LOCAL')/$value">                                                                                                          
        <edmx:Include Namespace="Org.OData.Validation.V1" Alias="Validation"/>                                                                                                                                                                                 
    </edmx:Reference>                                                                                                                                                                                                                                          
    <edmx:Reference Uri="../../catalogservice;v=2/Vocabularies(TechnicalName='%2FIWBEP%2FVOC_ANALYTICS',Version='0001',SAP__Origin='LOCAL')/$value">                                                                                                           
        <edmx:Include Namespace="com.sap.vocabularies.Analytics.v1" Alias="Analytics"/>                                                                                                                                                                        
    </edmx:Reference>                                                                                                                                                                                                                                          
    <edmx:Reference Uri="../../catalogservice;v=2/Vocabularies(TechnicalName='%2FIWBEP%2FVOC_HTML5',Version='0001',SAP__Origin='LOCAL')/$value">                                                                                                               
        <edmx:Include Namespace="com.sap.vocabularies.HTML5.v1" Alias="HTML5"/>                                                                                                                                                                                
    </edmx:Reference>                                                                                                                                                                                                                                          
    <edmx:Reference Uri="../../../sap/zui_o2_aprov_lib_emb/$metadata">                                                                                                                                                                                         
        <edmx:Include Namespace="ZUI_O2_APROV_LIB_EMB" Alias="SAP"/>                                                                                                                                                                                           
    </edmx:Reference>                                                                                                                                                                                                                                          
    <edmx:DataServices>                                                                                                                                                                                                                                        
        <Schema Namespace="zui_o2_aprov_lib_emb_van.v1" xmlns="http://docs.oasis-open.org/odata/ns/edm">                                                                                                                                                       
            <Annotations Target="cds_zui_app_aprov_lib_embarque.Lim_EmbarqueType/desc_org_venda">                                                                                                                                                              
                <Annotation Term="UI.Hidden"/>                                                                                                                                                                                                                 
            </Annotations>                                                                                                                                                                                                                                     
            <Annotations Target="cds_zui_app_aprov_lib_embarque.Lim_EmbarqueType/desc_esc_venda">                                                                                                                                                              
                <Annotation Term="UI.Hidden"/>                                                                                                                                                                                                                 
            </Annotations>                                                                                                                                                                                                                                     
            <Annotations Target="cds_zui_app_aprov_lib_embarque.Lim_EmbarqueType/desc_cliente">                                                                                                                                                                
                <Annotation Term="UI.Hidden"/>                                                                                                                                                                                                                 
            </Annotations>                                                                                                                                                                                                                                     
            <Annotations Target="cds_zui_app_aprov_lib_embarque.Lim_EmbarqueType/aprovar_ac">                                                                                                                                                                  
                <Annotation Term="UI.Hidden"/>                                                                                                                                                                                                                 
            </Annotations>                                                                                                                                                                                                                                     
            <Annotations Target="cds_zui_app_aprov_lib_embarque.Lim_EmbarqueType/rejeitar_ac">                                                                                                                                                                 
                <Annotation Term="UI.Hidden"/>                                                                                                                                                                                                                 
            </Annotations>                                                                                                                                                                                                                                     
            <Annotations Target="cds_zui_app_aprov_lib_embarque.Lim_EmbarqueType/to_Item_oc">                                                                                                                                                                  
                <Annotation Term="UI.Hidden"/>                                                                                                                                                                                                                 
            </Annotations>                                                                                                                                                                                                                                     
            <Annotations Target="cds_zui_app_aprov_lib_embarque.Lim_EmbarqueType">                                                                                                                                                                             
                <Annotation Term="UI.Facets">                                                                                                                                                                                                                  
                    <Collection>                                                                                                                                                                                                                               
                        <Record Type="UI.ReferenceFacet">                                                                                                                                                                                                      
                            <PropertyValue Property="Label" String="Lib. Embarque Insumo"/>                                                                                                                                                                    
                            <PropertyValue Property="ID" String="id"/>                                                                                                                                                                                         
                            <PropertyValue Property="Target" AnnotationPath="@UI.Identification"/>                                                                                                                                                             
                        </Record>                                                                                                                                                                                                                              
                        <Record Type="UI.ReferenceFacet">                                                                                                                                                                                                      
                            <PropertyValue Property="Label" String="Lib. Embarque Insumo"/>                                                                                                                                                                    
                            <PropertyValue Property="ID" String="items"/>                                                                                                                                                                                      
                            <PropertyValue Property="Target" AnnotationPath="to_Item/@UI.LineItem"/>                                                                                                                                                           
                        </Record>                                                                                                                                                                                                                              
                    </Collection>                                                                                                                                                                                                                              
                </Annotation>                                                                                                                                                                                                                                  
                <Annotation Term="UI.HeaderInfo">                                                                                                                                                                                                              
                    <Record>                                                                                                                                                                                                                                   
                        <PropertyValue Property="TypeName" String="Aprov. Lib. Embarque Insumo"/>                                                                                                                                                              
                        <PropertyValue Property="TypeNamePlural" String="Lib. Embarque Insumo"/>                                                                                                                                                               
                        <PropertyValue Property="Title">                                                                                                                                                                                                       
                            <Record Type="UI.DataField">                                                                                                                                                                                                       
                                <PropertyValue Property="Label" String="Lib. Embarque Insumo"/>                                                                                                                                                                
                                <PropertyValue Property="Value" Path="orgvenda"/>                                                                                                                                                                              
                            </Record>                                                                                                                                                                                                                          
                        </PropertyValue>                                                                                                                                                                                                                       
                    </Record>                                                                                                                                                                                                                                  
                </Annotation>                                                                                                                                                                                                                                  
                <Annotation Term="UI.Identification">                                                                                                                                                                                                          
                    <Collection>                                                                                                                                                                                                                               
                        <Record Type="UI.DataField">                                                                                                                                                                                                           
                            <PropertyValue Property="Value" Path="orgvenda"/>                                                                                                                                                                                  
                        </Record>                                                                                                                                                                                                                              
                        <Record Type="UI.DataField">                                                                                                                                                                                                           
                            <PropertyValue Property="Value" Path="esc_venda"/>                                                                                                                                                                                 
                        </Record>                                                                                                                                                                                                                              
                        <Record Type="UI.DataField">                                                                                                                                                                                                           
                            <PropertyValue Property="Value" Path="vbeln"/>                                                                                                                                                                                     
                        </Record>                                                                                                                                                                                                                              
                        <Record Type="UI.DataField">                                                                                                                                                                                                           
                            <PropertyValue Property="Value" Path="waerk"/>                                                                                                                                                                                     
                        </Record>                                                                                                                                                                                                                              
                        <Record Type="UI.DataField">                                                                                                                                                                                                           
                            <PropertyValue Property="Value" Path="cliente"/>                                                                                                                                                                                   
                        </Record>                                                                                                                                                                                                                              
                        <Record Type="UI.DataField">                                                                                                                                                                                                           
                            <PropertyValue Property="Value" Path="valor"/>                                                                                                                                                                                     
                        </Record>                                                                                                                                                                                                                              
                        <Record Type="UI.DataField">                                                                                                                                                                                                           
                            <PropertyValue Property="Value" Path="just_workflow"/>                                                                                                                                                                             
                        </Record>                                                                                                                                                                                                                              
                    </Collection>                                                                                                                                                                                                                              
                </Annotation>                                                                                                                                                                                                                                  
                <Annotation Term="UI.LineItem">                                                                                                                                                                                                                
                    <Collection>                                                                                                                                                                                                                               
                        <Record Type="UI.DataField">                                                                                                                                                                                                           
                            <PropertyValue Property="Value" Path="orgvenda"/>                                                                                                                                                                                  
                            <Annotation Term="UI.Importance" EnumMember="UI.ImportanceType/High"/>                                                                                                                                                             
                        </Record>                                                                                                                                                                                                                              
                        <Record Type="UI.DataField">                                                                                                                                                                                                           
                            <PropertyValue Property="Value" Path="esc_venda"/>                                                                                                                                                                                 
                        </Record>                                                                                                                                                                                                                              
                        <Record Type="UI.DataField">                                                                                                                                                                                                           
                            <PropertyValue Property="Value" Path="vbeln"/>                                                                                                                                                                                     
                        </Record>                                                                                                                                                                                                                              
                        <Record Type="UI.DataField">                                                                                                                                                                                                           
                            <PropertyValue Property="Value" Path="waerk"/>                                                                                                                                                                                     
                        </Record>                                                                                                                                                                                                                              
                        <Record Type="UI.DataField">                                                                                                                                                                                                           
                            <PropertyValue Property="Value" Path="cliente"/>                                                                                                                                                                                   
                        </Record>                                                                                                                                                                                                                              
                        <Record Type="UI.DataField">                                                                                                                                                                                                           
                            <PropertyValue Property="Value" Path="valor"/>                                                                                                                                                                                     
                        </Record>                                                                                                                                                                                                                              
                        <Record Type="UI.DataField">                                                                                                                                                                                                           
                            <PropertyValue Property="Value" Path="just_workflow"/>                                                                                                                                                                             
                        </Record>                                                                                                                                                                                                                              
                    </Collection>                                                                                                                                                                                                                              
                </Annotation>                                                                                                                                                                                                                                  
                <Annotation Term="UI.SelectionFields">                                                                                                                                                                                                         
                    <Collection>                                                                                                                                                                                                                               
                        <PropertyPath>orgvenda</PropertyPath>                                                                                                                                                                                                  
                    </Collection>                                                                                                                                                                                                                              
                </Annotation>                                                                                                                                                                                                                                  
            </Annotations>                                                                                                                                                                                                                                     
            <Annotations Target="cds_zui_app_aprov_lib_embarque.Lim_Embarque_ITType/desc_org_venda">                                                                                                                                                           
                <Annotation Term="UI.Hidden"/>                                                                                                                                                                                                                 
            </Annotations>                                                                                                                                                                                                                                     
            <Annotations Target="cds_zui_app_aprov_lib_embarque.Lim_Embarque_ITType/desc_esc_venda">                                                                                                                                                           
                <Annotation Term="UI.Hidden"/>                                                                                                                                                                                                                 
            </Annotations>                                                                                                                                                                                                                                     
            <Annotations Target="cds_zui_app_aprov_lib_embarque.Lim_Embarque_ITType/desc_material">                                                                                                                                                            
                <Annotation Term="UI.Hidden"/>                                                                                                                                                                                                                 
            </Annotations>                                                                                                                                                                                                                                     
            <Annotations Target="cds_zui_app_aprov_lib_embarque.Lim_Embarque_ITType/moeda_1">                                                                                                                                                                  
                <Annotation Term="UI.Hidden"/>                                                                                                                                                                                                                 
            </Annotations>                                                                                                                                                                                                                                     
            <Annotations Target="cds_zui_app_aprov_lib_embarque.Lim_Embarque_ITType">                                                                                                                                                                          
                <Annotation Term="UI.Facets">                                                                                                                                                                                                                  
                    <Collection>                                                                                                                                                                                                                               
                        <Record Type="UI.ReferenceFacet">                                                                                                                                                                                                      
                            <PropertyValue Property="Label" String="Lib. Embarque Insumo - Item"/>                                                                                                                                                             
                            <PropertyValue Property="ID" String="id"/>                                                                                                                                                                                         
                            <PropertyValue Property="Target" AnnotationPath="@UI.Identification"/>                                                                                                                                                             
                        </Record>                                                                                                                                                                                                                              
                    </Collection>                                                                                                                                                                                                                              
                </Annotation>                                                                                                                                                                                                                                  
                <Annotation Term="UI.HeaderInfo">                                                                                                                                                                                                              
                    <Record>                                                                                                                                                                                                                                   
                        <PropertyValue Property="TypeName" String="Aprov. Liberação Embarque -  Item"/>                                                                                                                                                        
                        <PropertyValue Property="TypeNamePlural" String="Liberação Embarque -  Item"/>                                                                                                                                                         
                        <PropertyValue Property="Title">                                                                                                                                                                                                       
                            <Record Type="UI.DataField">                                                                                                                                                                                                       
                                <PropertyValue Property="Label" String="Liberação Embarque -  Item"/>                                                                                                                                                          
                                <PropertyValue Property="Value" Path="orgvenda"/>                                                                                                                                                                              
                            </Record>                                                                                                                                                                                                                          
                        </PropertyValue>                                                                                                                                                                                                                       
                    </Record>                                                                                                                                                                                                                                  
                </Annotation>                                                                                                                                                                                                                                  
                <Annotation Term="UI.Identification">                                                                                                                                                                                                          
                    <Collection>                                                                                                                                                                                                                               
                        <Record Type="UI.DataField">                                                                                                                                                                                                           
                            <PropertyValue Property="Value" Path="orgvenda"/>                                                                                                                                                                                  
                        </Record>                                                                                                                                                                                                                              
                        <Record Type="UI.DataField">                                                                                                                                                                                                           
                            <PropertyValue Property="Value" Path="esc_venda"/>                                                                                                                                                                                 
                        </Record>                                                                                                                                                                                                                              
                        <Record Type="UI.DataField">                                                                                                                                                                                                           
                            <PropertyValue Property="Value" Path="vbeln"/>                                                                                                                                                                                     
                        </Record>                                                                                                                                                                                                                              
                        <Record Type="UI.DataField">                                                                                                                                                                                                           
                            <PropertyValue Property="Value" Path="posnr"/>                                                                                                                                                                                     
                        </Record>                                                                                                                                                                                                                              
                        <Record Type="UI.DataField">                                                                                                                                                                                                           
                            <PropertyValue Property="Value" Path="waerk"/>                                                                                                                                                                                     
                        </Record>                                                                                                                                                                                                                              
                        <Record Type="UI.DataField">                                                                                                                                                                                                           
                            <PropertyValue Property="Value" Path="matnr"/>                                                                                                                                                                                     
                        </Record>                                                                                                                                                                                                                              
                        <Record Type="UI.DataField">                                                                                                                                                                                                           
                            <PropertyValue Property="Value" Path="marca"/>                                                                                                                                                                                     
                        </Record>                                                                                                                                                                                                                              
                        <Record Type="UI.DataField">                                                                                                                                                                                                           
                            <PropertyValue Property="Value" Path="meins"/>                                                                                                                                                                                     
                        </Record>                                                                                                                                                                                                                              
                        <Record Type="UI.DataField">                                                                                                                                                                                                           
                            <PropertyValue Property="Value" Path="zmeng"/>                                                                                                                                                                                     
                        </Record>                                                                                                                                                                                                                              
                        <Record Type="UI.DataField">                                                                                                                                                                                                           
                            <PropertyValue Property="Value" Path="valor"/>                                                                                                                                                                                     
                        </Record>                                                                                                                                                                                                                              
                        <Record Type="UI.DataField">                                                                                                                                                                                                           
                            <PropertyValue Property="Value" Path="valor_usd"/>                                                                                                                                                                                 
                        </Record>                                                                                                                                                                                                                              
                        <Record Type="UI.DataField">                                                                                                                                                                                                           
                            <PropertyValue Property="Value" Path="doc_simulacao"/>                                                                                                                                                                             
                        </Record>                                                                                                                                                                                                                              
                    </Collection>                                                                                                                                                                                                                              
                </Annotation>                                                                                                                                                                                                                                  
                <Annotation Term="UI.LineItem">                                                                                                                                                                                                                
                    <Collection>                                                                                                                                                                                                                               
                        <Record Type="UI.DataField">                                                                                                                                                                                                           
                            <PropertyValue Property="Value" Path="orgvenda"/>                                                                                                                                                                                  
                            <Annotation Term="UI.Importance" EnumMember="UI.ImportanceType/High"/>                                                                                                                                                             
                        </Record>                                                                                                                                                                                                                              
                        <Record Type="UI.DataField">                                                                                                                                                                                                           
                            <PropertyValue Property="Value" Path="esc_venda"/>                                                                                                                                                                                 
                        </Record>                                                                                                                                                                                                                              
                        <Record Type="UI.DataField">                                                                                                                                                                                                           
                            <PropertyValue Property="Value" Path="vbeln"/>                                                                                                                                                                                     
                        </Record>                                                                                                                                                                                                                              
                        <Record Type="UI.DataField">                                                                                                                                                                                                           
                            <PropertyValue Property="Value" Path="posnr"/>                                                                                                                                                                                     
                        </Record>                                                                                                                                                                                                                              
                        <Record Type="UI.DataField">                                                                                                                                                                                                           
                            <PropertyValue Property="Value" Path="waerk"/>                                                                                                                                                                                     
                        </Record>                                                                                                                                                                                                                              
                        <Record Type="UI.DataField">                                                                                                                                                                                                           
                            <PropertyValue Property="Value" Path="matnr"/>                                                                                                                                                                                     
                        </Record>                                                                                                                                                                                                                              
                        <Record Type="UI.DataField">                                                                                                                                                                                                           
                            <PropertyValue Property="Value" Path="marca"/>                                                                                                                                                                                     
                        </Record>                                                                                                                                                                                                                              
                        <Record Type="UI.DataField">                                                                                                                                                                                                           
                            <PropertyValue Property="Value" Path="meins"/>                                                                                                                                                                                     
                        </Record>                                                                                                                                                                                                                              
                        <Record Type="UI.DataField">                                                                                                                                                                                                           
                            <PropertyValue Property="Value" Path="zmeng"/>                                                                                                                                                                                     
                        </Record>                                                                                                                                                                                                                              
                        <Record Type="UI.DataField">                                                                                                                                                                                                           
                            <PropertyValue Property="Value" Path="valor"/>                                                                                                                                                                                     
                        </Record>                                                                                                                                                                                                                              
                        <Record Type="UI.DataField">                                                                                                                                                                                                           
                            <PropertyValue Property="Value" Path="valor_usd"/>                                                                                                                                                                                 
                        </Record>                                                                                                                                                                                                                              
                        <Record Type="UI.DataField">                                                                                                                                                                                                           
                            <PropertyValue Property="Value" Path="doc_simulacao"/>                                                                                                                                                                             
                        </Record>                                                                                                                                                                                                                              
                    </Collection>                                                                                                                                                                                                                              
                </Annotation>                                                                                                                                                                                                                                  
                <Annotation Term="UI.SelectionFields">                                                                                                                                                                                                         
                    <Collection>                                                                                                                                                                                                                               
                        <PropertyPath>orgvenda</PropertyPath>                                                                                                                                                                                                  
                    </Collection>                                                                                                                                                                                                                              
                </Annotation>                                                                                                                                                                                                                                  
            </Annotations>                                                                                                                                                                                                                                     
        </Schema>                                                                                                                                                                                                                                              
    </edmx:DataServices>                                                                                                                                                                                                                                       
</edmx:Edmx>                                                                                                                                                                                                                                                   