<?xml version="1.0" encoding="utf-8"?>                                                                                                                                                                                                                         
<edmx:Edmx Version="4.0" xmlns:edmx="http://docs.oasis-open.org/odata/ns/edmx">                                                                                                                                                                                
    <edmx:Reference Uri="../../catalogservice;v=2/Vocabularies(TechnicalName='%2FIWBEP%2FVOC_COMMON',Version='0001',SAP__Origin='')/$value">                                                                                                                   
        <edmx:Include Namespace="com.sap.vocabularies.Common.v1" Alias="Common"/>                                                                                                                                                                              
    </edmx:Reference>                                                                                                                                                                                                                                          
    <edmx:Reference Uri="../../catalogservice;v=2/Vocabularies(TechnicalName='%2FIWBEP%2FVOC_UI',Version='0001',SAP__Origin='')/$value">                                                                                                                       
        <edmx:Include Namespace="com.sap.vocabularies.UI.v1" Alias="UI"/>                                                                                                                                                                                      
    </edmx:Reference>                                                                                                                                                                                                                                          
    <edmx:Reference Uri="../../catalogservice;v=2/Vocabularies(TechnicalName='%2FIWBEP%2FVOC_COMMUNICATION',Version='0001',SAP__Origin='')/$value">                                                                                                            
        <edmx:Include Namespace="com.sap.vocabularies.Communication.v1" Alias="Communication"/>                                                                                                                                                                
    </edmx:Reference>                                                                                                                                                                                                                                          
    <edmx:Reference Uri="../../catalogservice;v=2/Vocabularies(TechnicalName='%2FIWBEP%2FVOC_PERSONALDATA',Version='0001',SAP__Origin='')/$value">                                                                                                             
        <edmx:Include Namespace="com.sap.vocabularies.PersonalData.v1" Alias="PersonalData"/>                                                                                                                                                                  
    </edmx:Reference>                                                                                                                                                                                                                                          
    <edmx:Reference Uri="../../catalogservice;v=2/Vocabularies(TechnicalName='%2FIWBEP%2FVOC_VALIDATION',Version='0001',SAP__Origin='')/$value">                                                                                                               
        <edmx:Include Namespace="Org.OData.Validation.V1" Alias="Validation"/>                                                                                                                                                                                 
    </edmx:Reference>                                                                                                                                                                                                                                          
    <edmx:Reference Uri="../../catalogservice;v=2/Vocabularies(TechnicalName='%2FIWBEP%2FVOC_ANALYTICS',Version='0001',SAP__Origin='')/$value">                                                                                                                
        <edmx:Include Namespace="com.sap.vocabularies.Analytics.v1" Alias="Analytics"/>                                                                                                                                                                        
    </edmx:Reference>                                                                                                                                                                                                                                          
    <edmx:Reference Uri="../../catalogservice;v=2/Vocabularies(TechnicalName='%2FIWBEP%2FVOC_HTML5',Version='0001',SAP__Origin='')/$value">                                                                                                                    
        <edmx:Include Namespace="com.sap.vocabularies.HTML5.v1" Alias="HTML5"/>                                                                                                                                                                                
    </edmx:Reference>                                                                                                                                                                                                                                          
    <edmx:Reference Uri="../../../sap/zui_o2_sd_sol_ent_ins/$metadata">                                                                                                                                                                                        
        <edmx:Include Namespace="ZUI_O2_SD_SOL_ENT_INS" Alias="SAP"/>                                                                                                                                                                                          
    </edmx:Reference>                                                                                                                                                                                                                                          
    <edmx:DataServices>                                                                                                                                                                                                                                        
        <Schema Namespace="zui_o2_sd_sol_ent_ins_van.v1" xmlns="http://docs.oasis-open.org/odata/ns/edm">                                                                                                                                                      
            <Annotations Target="cds_zui_sd_sol_entrega_ins_anal.SolicitacoesType/solic_seq">                                                                                                                                                                  
                <Annotation Term="UI.Hidden"/>                                                                                                                                                                                                                 
            </Annotations>                                                                                                                                                                                                                                     
            <Annotations Target="cds_zui_sd_sol_entrega_ins_anal.SolicitacoesType/solic_ds_status">                                                                                                                                                            
                <Annotation Term="UI.Hidden"/>                                                                                                                                                                                                                 
            </Annotations>                                                                                                                                                                                                                                     
            <Annotations Target="cds_zui_sd_sol_entrega_ins_anal.SolicitacoesType/solic_data_cancelamento">                                                                                                                                                    
                <Annotation Term="UI.Hidden"/>                                                                                                                                                                                                                 
            </Annotations>                                                                                                                                                                                                                                     
            <Annotations Target="cds_zui_sd_sol_entrega_ins_anal.SolicitacoesType/solic_usuario_cancelamento">                                                                                                                                                 
                <Annotation Term="UI.Hidden"/>                                                                                                                                                                                                                 
            </Annotations>                                                                                                                                                                                                                                     
            <Annotations Target="cds_zui_sd_sol_entrega_ins_anal.SolicitacoesType/solic_data_entrega">                                                                                                                                                         
                <Annotation Term="UI.Hidden"/>                                                                                                                                                                                                                 
            </Annotations>                                                                                                                                                                                                                                     
            <Annotations Target="cds_zui_sd_sol_entrega_ins_anal.SolicitacoesType/solic_tipo_operacao">                                                                                                                                                        
                <Annotation Term="UI.Hidden"/>                                                                                                                                                                                                                 
            </Annotations>                                                                                                                                                                                                                                     
            <Annotations Target="cds_zui_sd_sol_entrega_ins_anal.SolicitacoesType/solic_origem_estoque">                                                                                                                                                       
                <Annotation Term="UI.Hidden"/>                                                                                                                                                                                                                 
            </Annotations>                                                                                                                                                                                                                                     
            <Annotations Target="cds_zui_sd_sol_entrega_ins_anal.SolicitacoesType/solic_pedido">                                                                                                                                                               
                <Annotation Term="UI.Hidden"/>                                                                                                                                                                                                                 
            </Annotations>                                                                                                                                                                                                                                     
            <Annotations Target="cds_zui_sd_sol_entrega_ins_anal.SolicitacoesType/solic_pedido_item">                                                                                                                                                          
                <Annotation Term="UI.Hidden"/>                                                                                                                                                                                                                 
            </Annotations>                                                                                                                                                                                                                                     
            <Annotations Target="cds_zui_sd_sol_entrega_ins_anal.SolicitacoesType/solic_fornecedor_arm">                                                                                                                                                       
                <Annotation Term="UI.Hidden"/>                                                                                                                                                                                                                 
            </Annotations>                                                                                                                                                                                                                                     
            <Annotations Target="cds_zui_sd_sol_entrega_ins_anal.SolicitacoesType/solic_lote">                                                                                                                                                                 
                <Annotation Term="UI.Hidden"/>                                                                                                                                                                                                                 
            </Annotations>                                                                                                                                                                                                                                     
            <Annotations Target="cds_zui_sd_sol_entrega_ins_anal.SolicitacoesType/solic_marca">                                                                                                                                                                
                <Annotation Term="UI.Hidden"/>                                                                                                                                                                                                                 
            </Annotations>                                                                                                                                                                                                                                     
            <Annotations Target="cds_zui_sd_sol_entrega_ins_anal.SolicitacoesType/solic_carga_automatica">                                                                                                                                                     
                <Annotation Term="UI.Hidden"/>                                                                                                                                                                                                                 
            </Annotations>                                                                                                                                                                                                                                     
            <Annotations Target="cds_zui_sd_sol_entrega_ins_anal.SolicitacoesType/solic_flexibilidade">                                                                                                                                                        
                <Annotation Term="UI.Hidden"/>                                                                                                                                                                                                                 
            </Annotations>                                                                                                                                                                                                                                     
            <Annotations Target="cds_zui_sd_sol_entrega_ins_anal.SolicitacoesType/solic_prioridade">                                                                                                                                                           
                <Annotation Term="UI.Hidden"/>                                                                                                                                                                                                                 
            </Annotations>                                                                                                                                                                                                                                     
            <Annotations Target="cds_zui_sd_sol_entrega_ins_anal.SolicitacoesType/solic_transf_no_fornecedor">                                                                                                                                                 
                <Annotation Term="UI.Hidden"/>                                                                                                                                                                                                                 
            </Annotations>                                                                                                                                                                                                                                     
            <Annotations Target="cds_zui_sd_sol_entrega_ins_anal.SolicitacoesType/distrib_seq">                                                                                                                                                                
                <Annotation Term="UI.Hidden"/>                                                                                                                                                                                                                 
            </Annotations>                                                                                                                                                                                                                                     
            <Annotations Target="cds_zui_sd_sol_entrega_ins_anal.SolicitacoesType/distrib_quantidade">                                                                                                                                                         
                <Annotation Term="UI.Hidden"/>                                                                                                                                                                                                                 
            </Annotations>                                                                                                                                                                                                                                     
            <Annotations Target="cds_zui_sd_sol_entrega_ins_anal.SolicitacoesType/distrib_data">                                                                                                                                                               
                <Annotation Term="UI.Hidden"/>                                                                                                                                                                                                                 
            </Annotations>                                                                                                                                                                                                                                     
            <Annotations Target="cds_zui_sd_sol_entrega_ins_anal.SolicitacoesType/distrib_usuario">                                                                                                                                                            
                <Annotation Term="UI.Hidden"/>                                                                                                                                                                                                                 
            </Annotations>                                                                                                                                                                                                                                     
            <Annotations Target="cds_zui_sd_sol_entrega_ins_anal.SolicitacoesType/distrib_status">                                                                                                                                                             
                <Annotation Term="UI.Hidden"/>                                                                                                                                                                                                                 
            </Annotations>                                                                                                                                                                                                                                     
            <Annotations Target="cds_zui_sd_sol_entrega_ins_anal.SolicitacoesType/distrib_ds_status">                                                                                                                                                          
                <Annotation Term="UI.Hidden"/>                                                                                                                                                                                                                 
            </Annotations>                                                                                                                                                                                                                                     
            <Annotations Target="cds_zui_sd_sol_entrega_ins_anal.SolicitacoesType/distrib_data_cancelamento">                                                                                                                                                  
                <Annotation Term="UI.Hidden"/>                                                                                                                                                                                                                 
            </Annotations>                                                                                                                                                                                                                                     
            <Annotations Target="cds_zui_sd_sol_entrega_ins_anal.SolicitacoesType/distrib_usuario_cancelamento">                                                                                                                                               
                <Annotation Term="UI.Hidden"/>                                                                                                                                                                                                                 
            </Annotations>                                                                                                                                                                                                                                     
            <Annotations Target="cds_zui_sd_sol_entrega_ins_anal.SolicitacoesType/carga_nro">                                                                                                                                                                  
                <Annotation Term="UI.Hidden"/>                                                                                                                                                                                                                 
            </Annotations>                                                                                                                                                                                                                                     
            <Annotations Target="cds_zui_sd_sol_entrega_ins_anal.SolicitacoesType/carga_quantidade">                                                                                                                                                           
                <Annotation Term="UI.Hidden"/>                                                                                                                                                                                                                 
            </Annotations>                                                                                                                                                                                                                                     
            <Annotations Target="cds_zui_sd_sol_entrega_ins_anal.SolicitacoesType/carga_data_criacao">                                                                                                                                                         
                <Annotation Term="UI.Hidden"/>                                                                                                                                                                                                                 
            </Annotations>                                                                                                                                                                                                                                     
            <Annotations Target="cds_zui_sd_sol_entrega_ins_anal.SolicitacoesType/carga_usuario_criacao">                                                                                                                                                      
                <Annotation Term="UI.Hidden"/>                                                                                                                                                                                                                 
            </Annotations>                                                                                                                                                                                                                                     
            <Annotations Target="cds_zui_sd_sol_entrega_ins_anal.SolicitacoesType/carga_data_envio_cotacao">                                                                                                                                                   
                <Annotation Term="UI.Hidden"/>                                                                                                                                                                                                                 
            </Annotations>                                                                                                                                                                                                                                     
            <Annotations Target="cds_zui_sd_sol_entrega_ins_anal.SolicitacoesType/carga_data_frete_contratado">                                                                                                                                                
                <Annotation Term="UI.Hidden"/>                                                                                                                                                                                                                 
            </Annotations>                                                                                                                                                                                                                                     
            <Annotations Target="cds_zui_sd_sol_entrega_ins_anal.SolicitacoesType/carga_data_aut_embarque">                                                                                                                                                    
                <Annotation Term="UI.Hidden"/>                                                                                                                                                                                                                 
            </Annotations>                                                                                                                                                                                                                                     
            <Annotations Target="cds_zui_sd_sol_entrega_ins_anal.SolicitacoesType/carga_data_carregamento">                                                                                                                                                    
                <Annotation Term="UI.Hidden"/>                                                                                                                                                                                                                 
            </Annotations>                                                                                                                                                                                                                                     
            <Annotations Target="cds_zui_sd_sol_entrega_ins_anal.SolicitacoesType/carga_data_conferencia">                                                                                                                                                     
                <Annotation Term="UI.Hidden"/>                                                                                                                                                                                                                 
            </Annotations>                                                                                                                                                                                                                                     
            <Annotations Target="cds_zui_sd_sol_entrega_ins_anal.SolicitacoesType/carga_data_finaliza_fatura">                                                                                                                                                 
                <Annotation Term="UI.Hidden"/>                                                                                                                                                                                                                 
            </Annotations>                                                                                                                                                                                                                                     
            <Annotations Target="cds_zui_sd_sol_entrega_ins_anal.SolicitacoesType/carga_data_cancelamento">                                                                                                                                                    
                <Annotation Term="UI.Hidden"/>                                                                                                                                                                                                                 
            </Annotations>                                                                                                                                                                                                                                     
            <Annotations Target="cds_zui_sd_sol_entrega_ins_anal.SolicitacoesType/carga_hora_cancelamento">                                                                                                                                                    
                <Annotation Term="UI.Hidden"/>                                                                                                                                                                                                                 
            </Annotations>                                                                                                                                                                                                                                     
            <Annotations Target="cds_zui_sd_sol_entrega_ins_anal.SolicitacoesType/carga_usuario_cancelamento">                                                                                                                                                 
                <Annotation Term="UI.Hidden"/>                                                                                                                                                                                                                 
            </Annotations>                                                                                                                                                                                                                                     
            <Annotations Target="cds_zui_sd_sol_entrega_ins_anal.SolicitacoesType/carga_status">                                                                                                                                                               
                <Annotation Term="UI.Hidden"/>                                                                                                                                                                                                                 
            </Annotations>                                                                                                                                                                                                                                     
            <Annotations Target="cds_zui_sd_sol_entrega_ins_anal.SolicitacoesType/carga_ds_stauts">                                                                                                                                                            
                <Annotation Term="UI.Hidden"/>                                                                                                                                                                                                                 
            </Annotations>                                                                                                                                                                                                                                     
            <Annotations Target="cds_zui_sd_sol_entrega_ins_anal.SolicitacoesType/carga_status_entrega">                                                                                                                                                       
                <Annotation Term="UI.Hidden"/>                                                                                                                                                                                                                 
            </Annotations>                                                                                                                                                                                                                                     
            <Annotations Target="cds_zui_sd_sol_entrega_ins_anal.SolicitacoesType/dias_distribuicao">                                                                                                                                                          
                <Annotation Term="UI.Hidden"/>                                                                                                                                                                                                                 
            </Annotations>                                                                                                                                                                                                                                     
            <Annotations Target="cds_zui_sd_sol_entrega_ins_anal.SolicitacoesType/dias_criacao_carga">                                                                                                                                                         
                <Annotation Term="UI.Hidden"/>                                                                                                                                                                                                                 
            </Annotations>                                                                                                                                                                                                                                     
            <Annotations Target="cds_zui_sd_sol_entrega_ins_anal.SolicitacoesType/dias_envio_cotacao_carga">                                                                                                                                                   
                <Annotation Term="UI.Hidden"/>                                                                                                                                                                                                                 
            </Annotations>                                                                                                                                                                                                                                     
            <Annotations Target="cds_zui_sd_sol_entrega_ins_anal.SolicitacoesType/dias_contratacao_frete_carga">                                                                                                                                               
                <Annotation Term="UI.Hidden"/>                                                                                                                                                                                                                 
            </Annotations>                                                                                                                                                                                                                                     
            <Annotations Target="cds_zui_sd_sol_entrega_ins_anal.SolicitacoesType/dias_autorizacao_emb_carga">                                                                                                                                                 
                <Annotation Term="UI.Hidden"/>                                                                                                                                                                                                                 
            </Annotations>                                                                                                                                                                                                                                     
            <Annotations Target="cds_zui_sd_sol_entrega_ins_anal.SolicitacoesType/dias_carregamento_carga">                                                                                                                                                    
                <Annotation Term="UI.Hidden"/>                                                                                                                                                                                                                 
            </Annotations>                                                                                                                                                                                                                                     
            <Annotations Target="cds_zui_sd_sol_entrega_ins_anal.SolicitacoesType/dias_conferencia_carga">                                                                                                                                                     
                <Annotation Term="UI.Hidden"/>                                                                                                                                                                                                                 
            </Annotations>                                                                                                                                                                                                                                     
            <Annotations Target="cds_zui_sd_sol_entrega_ins_anal.SolicitacoesType/dias_faturamento_carga">                                                                                                                                                     
                <Annotation Term="UI.Hidden"/>                                                                                                                                                                                                                 
            </Annotations>                                                                                                                                                                                                                                     
            <Annotations Target="cds_zui_sd_sol_entrega_ins_anal.SolicitacoesType/situacao_distrib">                                                                                                                                                           
                <Annotation Term="UI.Hidden"/>                                                                                                                                                                                                                 
            </Annotations>                                                                                                                                                                                                                                     
            <Annotations Target="cds_zui_sd_sol_entrega_ins_anal.SolicitacoesType/situacao_criacao_carga">                                                                                                                                                     
                <Annotation Term="UI.Hidden"/>                                                                                                                                                                                                                 
            </Annotations>                                                                                                                                                                                                                                     
            <Annotations Target="cds_zui_sd_sol_entrega_ins_anal.SolicitacoesType/situacao_envio_cotacao">                                                                                                                                                     
                <Annotation Term="UI.Hidden"/>                                                                                                                                                                                                                 
            </Annotations>                                                                                                                                                                                                                                     
            <Annotations Target="cds_zui_sd_sol_entrega_ins_anal.SolicitacoesType/situacao_contratao_frete">                                                                                                                                                   
                <Annotation Term="UI.Hidden"/>                                                                                                                                                                                                                 
            </Annotations>                                                                                                                                                                                                                                     
            <Annotations Target="cds_zui_sd_sol_entrega_ins_anal.SolicitacoesType/situacao_autorizacao_embarque">                                                                                                                                              
                <Annotation Term="UI.Hidden"/>                                                                                                                                                                                                                 
            </Annotations>                                                                                                                                                                                                                                     
            <Annotations Target="cds_zui_sd_sol_entrega_ins_anal.SolicitacoesType/situacao_carregamento">                                                                                                                                                      
                <Annotation Term="UI.Hidden"/>                                                                                                                                                                                                                 
            </Annotations>                                                                                                                                                                                                                                     
            <Annotations Target="cds_zui_sd_sol_entrega_ins_anal.SolicitacoesType/situacao_conferencia">                                                                                                                                                       
                <Annotation Term="UI.Hidden"/>                                                                                                                                                                                                                 
            </Annotations>                                                                                                                                                                                                                                     
            <Annotations Target="cds_zui_sd_sol_entrega_ins_anal.SolicitacoesType/situacao_faturamento">                                                                                                                                                       
                <Annotation Term="UI.Hidden"/>                                                                                                                                                                                                                 
            </Annotations>                                                                                                                                                                                                                                     
            <Annotations Target="cds_zui_sd_sol_entrega_ins_anal.SolicitacoesType">                                                                                                                                                                            
                <Annotation Term="UI.Facets">                                                                                                                                                                                                                  
                    <Collection>                                                                                                                                                                                                                               
                        <Record Type="UI.ReferenceFacet">                                                                                                                                                                                                      
                            <PropertyValue Property="Label" String="Solicitaes Entrega"/>                                                                                                                                                                    
                            <PropertyValue Property="ID" String="Tela1"/>                                                                                                                                                                                      
                            <PropertyValue Property="Target" AnnotationPath="@UI.Identification"/>                                                                                                                                                             
                        </Record>                                                                                                                                                                                                                              
                    </Collection>                                                                                                                                                                                                                              
                </Annotation>                                                                                                                                                                                                                                  
                <Annotation Term="UI.HeaderInfo">                                                                                                                                                                                                              
                    <Record>                                                                                                                                                                                                                                   
                        <PropertyValue Property="TypeName" String="Solicitao Entrega Insumos"/>                                                                                                                                                              
                        <PropertyValue Property="TypeNamePlural" String="Solicitaes de Entrega de Insumos"/>                                                                                                                                                 
                        <PropertyValue Property="Title">                                                                                                                                                                                                       
                            <Record Type="UI.DataField">                                                                                                                                                                                                       
                                <PropertyValue Property="Label" String="Solicitao Entrega"/>                                                                                                                                                                 
                                <PropertyValue Property="Value" Path="solic_nro"/>                                                                                                                                                                             
                            </Record>                                                                                                                                                                                                                          
                        </PropertyValue>                                                                                                                                                                                                                       
                    </Record>                                                                                                                                                                                                                                  
                </Annotation>                                                                                                                                                                                                                                  
                <Annotation Term="UI.Identification">                                                                                                                                                                                                          
                    <Collection>                                                                                                                                                                                                                               
                        <Record Type="UI.DataField">                                                                                                                                                                                                           
                            <PropertyValue Property="Value" Path="solic_nro"/>                                                                                                                                                                                 
                        </Record>                                                                                                                                                                                                                              
                        <Record Type="UI.DataField">                                                                                                                                                                                                           
                            <PropertyValue Property="Value" Path="solic_ordem"/>                                                                                                                                                                               
                        </Record>                                                                                                                                                                                                                              
                        <Record Type="UI.DataField">                                                                                                                                                                                                           
                            <PropertyValue Property="Value" Path="solic_ordem_item"/>                                                                                                                                                                          
                        </Record>                                                                                                                                                                                                                              
                        <Record Type="UI.DataField">                                                                                                                                                                                                           
                            <PropertyValue Property="Value" Path="solic_nro_sol_origem"/>                                                                                                                                                                      
                        </Record>                                                                                                                                                                                                                              
                        <Record Type="UI.DataField">                                                                                                                                                                                                           
                            <PropertyValue Property="Value" Path="solic_organizacao_venda"/>                                                                                                                                                                   
                        </Record>                                                                                                                                                                                                                              
                        <Record Type="UI.DataField">                                                                                                                                                                                                           
                            <PropertyValue Property="Value" Path="solic_setor_atividade"/>                                                                                                                                                                     
                        </Record>                                                                                                                                                                                                                              
                        <Record Type="UI.DataField">                                                                                                                                                                                                           
                            <PropertyValue Property="Value" Path="solic_escritorio_venda"/>                                                                                                                                                                    
                        </Record>                                                                                                                                                                                                                              
                        <Record Type="UI.DataField">                                                                                                                                                                                                           
                            <PropertyValue Property="Value" Path="solic_centro_faturamento"/>                                                                                                                                                                  
                        </Record>                                                                                                                                                                                                                              
                        <Record Type="UI.DataField">                                                                                                                                                                                                           
                            <PropertyValue Property="Value" Path="solic_tipo_ov"/>                                                                                                                                                                             
                        </Record>                                                                                                                                                                                                                              
                        <Record Type="UI.DataField">                                                                                                                                                                                                           
                            <PropertyValue Property="Value" Path="solic_quantidade"/>                                                                                                                                                                          
                        </Record>                                                                                                                                                                                                                              
                        <Record Type="UI.DataField">                                                                                                                                                                                                           
                            <PropertyValue Property="Value" Path="solic_unidade"/>                                                                                                                                                                             
                        </Record>                                                                                                                                                                                                                              
                        <Record Type="UI.DataField">                                                                                                                                                                                                           
                            <PropertyValue Property="Value" Path="solic_data"/>                                                                                                                                                                                
                        </Record>                                                                                                                                                                                                                              
                        <Record Type="UI.DataField">                                                                                                                                                                                                           
                            <PropertyValue Property="Value" Path="solic_data_sol_raiz"/>                                                                                                                                                                       
                        </Record>                                                                                                                                                                                                                              
                        <Record Type="UI.DataField">                                                                                                                                                                                                           
                            <PropertyValue Property="Value" Path="solic_nro_sol_raiz"/>                                                                                                                                                                        
                        </Record>                                                                                                                                                                                                                              
                        <Record Type="UI.DataField">                                                                                                                                                                                                           
                            <PropertyValue Property="Value" Path="solic_usuario_criacao"/>                                                                                                                                                                     
                        </Record>                                                                                                                                                                                                                              
                        <Record Type="UI.DataField">                                                                                                                                                                                                           
                            <PropertyValue Property="Value" Path="solic_status"/>                                                                                                                                                                              
                        </Record>                                                                                                                                                                                                                              
                    </Collection>                                                                                                                                                                                                                              
                </Annotation>                                                                                                                                                                                                                                  
                <Annotation Term="UI.LineItem">                                                                                                                                                                                                                
                    <Collection>                                                                                                                                                                                                                               
                        <Record Type="UI.DataField">                                                                                                                                                                                                           
                            <PropertyValue Property="Value" Path="solic_nro"/>                                                                                                                                                                                 
                        </Record>                                                                                                                                                                                                                              
                        <Record Type="UI.DataField">                                                                                                                                                                                                           
                            <PropertyValue Property="Value" Path="solic_ordem"/>                                                                                                                                                                               
                        </Record>                                                                                                                                                                                                                              
                        <Record Type="UI.DataField">                                                                                                                                                                                                           
                            <PropertyValue Property="Value" Path="solic_ordem_item"/>                                                                                                                                                                          
                        </Record>                                                                                                                                                                                                                              
                        <Record Type="UI.DataField">                                                                                                                                                                                                           
                            <PropertyValue Property="Value" Path="solic_nro_sol_origem"/>                                                                                                                                                                      
                        </Record>                                                                                                                                                                                                                              
                        <Record Type="UI.DataField">                                                                                                                                                                                                           
                            <PropertyValue Property="Value" Path="solic_organizacao_venda"/>                                                                                                                                                                   
                        </Record>                                                                                                                                                                                                                              
                        <Record Type="UI.DataField">                                                                                                                                                                                                           
                            <PropertyValue Property="Value" Path="solic_setor_atividade"/>                                                                                                                                                                     
                        </Record>                                                                                                                                                                                                                              
                        <Record Type="UI.DataField">                                                                                                                                                                                                           
                            <PropertyValue Property="Value" Path="solic_escritorio_venda"/>                                                                                                                                                                    
                        </Record>                                                                                                                                                                                                                              
                        <Record Type="UI.DataField">                                                                                                                                                                                                           
                            <PropertyValue Property="Value" Path="solic_centro_faturamento"/>                                                                                                                                                                  
                        </Record>                                                                                                                                                                                                                              
                        <Record Type="UI.DataField">                                                                                                                                                                                                           
                            <PropertyValue Property="Value" Path="solic_tipo_ov"/>                                                                                                                                                                             
                        </Record>                                                                                                                                                                                                                              
                        <Record Type="UI.DataField">                                                                                                                                                                                                           
                            <PropertyValue Property="Value" Path="solic_quantidade"/>                                                                                                                                                                          
                        </Record>                                                                                                                                                                                                                              
                        <Record Type="UI.DataField">                                                                                                                                                                                                           
                            <PropertyValue Property="Value" Path="solic_unidade"/>                                                                                                                                                                             
                        </Record>                                                                                                                                                                                                                              
                        <Record Type="UI.DataField">                                                                                                                                                                                                           
                            <PropertyValue Property="Value" Path="solic_data"/>                                                                                                                                                                                
                        </Record>                                                                                                                                                                                                                              
                        <Record Type="UI.DataField">                                                                                                                                                                                                           
                            <PropertyValue Property="Value" Path="solic_data_sol_raiz"/>                                                                                                                                                                       
                        </Record>                                                                                                                                                                                                                              
                        <Record Type="UI.DataField">                                                                                                                                                                                                           
                            <PropertyValue Property="Value" Path="solic_nro_sol_raiz"/>                                                                                                                                                                        
                        </Record>                                                                                                                                                                                                                              
                        <Record Type="UI.DataField">                                                                                                                                                                                                           
                            <PropertyValue Property="Value" Path="solic_usuario_criacao"/>                                                                                                                                                                     
                        </Record>                                                                                                                                                                                                                              
                        <Record Type="UI.DataField">                                                                                                                                                                                                           
                            <PropertyValue Property="Value" Path="solic_status"/>                                                                                                                                                                              
                        </Record>                                                                                                                                                                                                                              
                    </Collection>                                                                                                                                                                                                                              
                </Annotation>                                                                                                                                                                                                                                  
                <Annotation Term="UI.SelectionFields">                                                                                                                                                                                                         
                    <Collection>                                                                                                                                                                                                                               
                        <PropertyPath>solic_nro</PropertyPath>                                                                                                                                                                                                 
                        <PropertyPath>solic_ordem</PropertyPath>                                                                                                                                                                                               
                        <PropertyPath>solic_ordem_item</PropertyPath>                                                                                                                                                                                          
                        <PropertyPath>solic_nro_sol_origem</PropertyPath>                                                                                                                                                                                      
                        <PropertyPath>solic_organizacao_venda</PropertyPath>                                                                                                                                                                                   
                        <PropertyPath>solic_escritorio_venda</PropertyPath>                                                                                                                                                                                    
                        <PropertyPath>solic_setor_atividade</PropertyPath>                                                                                                                                                                                     
                        <PropertyPath>solic_centro_faturamento</PropertyPath>                                                                                                                                                                                  
                        <PropertyPath>solic_tipo_ov</PropertyPath>                                                                                                                                                                                             
                        <PropertyPath>solic_quantidade</PropertyPath>                                                                                                                                                                                          
                        <PropertyPath>solic_unidade</PropertyPath>                                                                                                                                                                                             
                        <PropertyPath>solic_data</PropertyPath>                                                                                                                                                                                                
                        <PropertyPath>solic_data_sol_raiz</PropertyPath>                                                                                                                                                                                       
                        <PropertyPath>solic_nro_sol_raiz</PropertyPath>                                                                                                                                                                                        
                        <PropertyPath>solic_usuario_criacao</PropertyPath>                                                                                                                                                                                     
                        <PropertyPath>solic_status</PropertyPath>                                                                                                                                                                                              
                    </Collection>                                                                                                                                                                                                                              
                </Annotation>                                                                                                                                                                                                                                  
            </Annotations>                                                                                                                                                                                                                                     
        </Schema>                                                                                                                                                                                                                                              
    </edmx:DataServices>                                                                                                                                                                                                                                       
</edmx:Edmx>                                                                                                                                                                                                                                                   