<?xml version="1.0" encoding="utf-8"?>
<abapGit version="v1.0.0" serializer="LCL_OBJECT_ENQU" serializer_version="v1.0.0">
 <asx:abap xmlns:asx="http://www.sap.com/abapxml" version="1.0">
  <asx:values>
   <DD25V>
    <VIEWNAME>EZSDT0053</VIEWNAME>
    <DDLANGUAGE>P</DDLANGUAGE>
    <AGGTYPE>E</AGGTYPE>
    <ROOTTAB>TRDIR</ROOTTAB>
    <DDTEXT>Block Transação ZSDT0053</DDTEXT>
   </DD25V>
   <DD26E_TABLE>
    <DD26E>
     <VIEWNAME>EZSDT0053</VIEWNAME>
     <TABNAME>TRDIR</TABNAME>
     <TABPOS>0001</TABPOS>
     <FORTABNAME>TRDIR</FORTABNAME>
     <ENQMODE>E</ENQMODE>
    </DD26E>
   </DD26E_TABLE>
   <DD27P_TABLE>
    <DD27P>
     <VIEWNAME>EZSDT0053</VIEWNAME>
     <OBJPOS>0001</OBJPOS>
     <VIEWFIELD>NAME</VIEWFIELD>
     <TABNAME>TRDIR</TABNAME>
     <FIELDNAME>NAME</FIELDNAME>
     <KEYFLAG>X</KEYFLAG>
     <ENQMODE>E</ENQMODE>
    </DD27P>
   </DD27P_TABLE>
  </asx:values>
 </asx:abap>
</abapGit>
