<?xml version="1.0" encoding="utf-8"?>
<abapGit version="v1.0.0" serializer="LCL_OBJECT_SSST" serializer_version="v1.0.0">
 <asx:abap xmlns:asx="http://www.sap.com/abapxml" version="1.0">
  <asx:values>
   <HEADER>
    <STYLENAME>ZFIS002</STYLENAME>
    <MASTERLANG>P</MASTERLANG>
    <LANGU>P</LANGU>
    <CAPTION>Estilo ZFIS002</CAPTION>
    <V_CAPTION>Estilo ZFIS002</V_CAPTION>
    <TDFIRSTPAR>P1</TDFIRSTPAR>
    <CPI>10.0</CPI>
    <LPI>6.0</LPI>
    <TDTABDIST>1.0</TDTABDIST>
    <TDTABDISTU>CM</TDTABDISTU>
    <ACTIVE>A</ACTIVE>
    <TDFAMILY>COURIER</TDFAMILY>
    <TDHEIGHT>120</TDHEIGHT>
   </HEADER>
   <SSFPARAS>
    <SSFPARAS>
     <ACTIVE>A</ACTIVE>
     <STYLENAME>ZFIS002</STYLENAME>
     <TDPARGRAPH>H1</TDPARGRAPH>
     <TDPJUSTIFY>CENTER</TDPJUSTIFY>
     <TDPLDIST>1.0</TDPLDIST>
     <TDPLDISTU>LN</TDPLDISTU>
     <TDPTOPU>CM</TDPTOPU>
     <TDPBOTU>CM</TDPBOTU>
     <TDPLEFTU>CM</TDPLEFTU>
     <TDPRIGHTU>CM</TDPRIGHTU>
     <TDPENTRYU>CM</TDPENTRYU>
     <TDNUMLEFTU>CM</TDNUMLEFTU>
     <TDFAMILY>HELVE</TDFAMILY>
     <TDHEIGHT>100</TDHEIGHT>
     <TDBOLD>*</TDBOLD>
     <TDITALIC>*</TDITALIC>
     <TDUNDERLIN>*</TDUNDERLIN>
     <LANGU>P</LANGU>
     <CAPTION>Cabeçalho 01 - Centralizado</CAPTION>
    </SSFPARAS>
    <SSFPARAS>
     <ACTIVE>A</ACTIVE>
     <STYLENAME>ZFIS002</STYLENAME>
     <TDPARGRAPH>H2</TDPARGRAPH>
     <TDPJUSTIFY>LEFT</TDPJUSTIFY>
     <TDPLDIST>1.0</TDPLDIST>
     <TDPLDISTU>LN</TDPLDISTU>
     <TDPTOPU>CM</TDPTOPU>
     <TDPBOTU>CM</TDPBOTU>
     <TDPLEFTU>CM</TDPLEFTU>
     <TDPRIGHTU>CM</TDPRIGHTU>
     <TDPENTRYU>CM</TDPENTRYU>
     <TDFAMILY>HELVE</TDFAMILY>
     <TDHEIGHT>100</TDHEIGHT>
     <TDBOLD>*</TDBOLD>
     <TDITALIC>*</TDITALIC>
     <TDUNDERLIN>*</TDUNDERLIN>
     <LANGU>P</LANGU>
     <CAPTION>Cabeçalho 02 - Esquerda</CAPTION>
    </SSFPARAS>
    <SSFPARAS>
     <ACTIVE>A</ACTIVE>
     <STYLENAME>ZFIS002</STYLENAME>
     <TDPARGRAPH>P1</TDPARGRAPH>
     <TDPJUSTIFY>LEFT</TDPJUSTIFY>
     <TDPLDIST>1.0</TDPLDIST>
     <TDPLDISTU>LN</TDPLDISTU>
     <TDPTOPU>CM</TDPTOPU>
     <TDPBOTU>CM</TDPBOTU>
     <TDPLEFTU>CM</TDPLEFTU>
     <TDPRIGHTU>CM</TDPRIGHTU>
     <TDPENTRYU>CM</TDPENTRYU>
     <TDNUMLEFTU>CM</TDNUMLEFTU>
     <TDFAMILY>HELVE</TDFAMILY>
     <TDHEIGHT>100</TDHEIGHT>
     <TDBOLD>*</TDBOLD>
     <TDITALIC>*</TDITALIC>
     <TDUNDERLIN>*</TDUNDERLIN>
     <LANGU>P</LANGU>
     <CAPTION>Parágrafo Standard</CAPTION>
    </SSFPARAS>
    <SSFPARAS>
     <ACTIVE>A</ACTIVE>
     <STYLENAME>ZFIS002</STYLENAME>
     <TDPARGRAPH>R1</TDPARGRAPH>
     <TDPJUSTIFY>CENTER</TDPJUSTIFY>
     <TDPLDIST>1.0</TDPLDIST>
     <TDPLDISTU>LN</TDPLDISTU>
     <TDPTOPU>CM</TDPTOPU>
     <TDPBOTU>CM</TDPBOTU>
     <TDPLEFTU>CM</TDPLEFTU>
     <TDPRIGHTU>CM</TDPRIGHTU>
     <TDPENTRYU>CM</TDPENTRYU>
     <TDNUMLEFTU>CM</TDNUMLEFTU>
     <TDFAMILY>HELVE</TDFAMILY>
     <TDHEIGHT>120</TDHEIGHT>
     <TDBOLD>*</TDBOLD>
     <TDITALIC>*</TDITALIC>
     <TDUNDERLIN>*</TDUNDERLIN>
     <LANGU>P</LANGU>
     <CAPTION>Resumo - Centralizado</CAPTION>
    </SSFPARAS>
    <SSFPARAS>
     <ACTIVE>A</ACTIVE>
     <STYLENAME>ZFIS002</STYLENAME>
     <TDPARGRAPH>R2</TDPARGRAPH>
     <TDPJUSTIFY>LEFT</TDPJUSTIFY>
     <TDPLDIST>1.0</TDPLDIST>
     <TDPLDISTU>LN</TDPLDISTU>
     <TDPTOPU>CM</TDPTOPU>
     <TDPBOTU>CM</TDPBOTU>
     <TDPLEFT>0.2</TDPLEFT>
     <TDPLEFTU>CM</TDPLEFTU>
     <TDPRIGHTU>CM</TDPRIGHTU>
     <TDPENTRYU>CM</TDPENTRYU>
     <TDNUMLEFTU>CM</TDNUMLEFTU>
     <TDFAMILY>HELVE</TDFAMILY>
     <TDHEIGHT>120</TDHEIGHT>
     <TDBOLD>*</TDBOLD>
     <TDITALIC>*</TDITALIC>
     <TDUNDERLIN>*</TDUNDERLIN>
     <LANGU>P</LANGU>
     <CAPTION>Resumo -  Esquerda</CAPTION>
    </SSFPARAS>
    <SSFPARAS>
     <ACTIVE>A</ACTIVE>
     <STYLENAME>ZFIS002</STYLENAME>
     <TDPARGRAPH>R3</TDPARGRAPH>
     <TDPJUSTIFY>RIGHT</TDPJUSTIFY>
     <TDPLDIST>1.0</TDPLDIST>
     <TDPLDISTU>LN</TDPLDISTU>
     <TDPTOPU>CM</TDPTOPU>
     <TDPBOTU>CM</TDPBOTU>
     <TDPLEFTU>CM</TDPLEFTU>
     <TDPRIGHT>0.2</TDPRIGHT>
     <TDPRIGHTU>CM</TDPRIGHTU>
     <TDPENTRYU>CM</TDPENTRYU>
     <TDNUMLEFTU>CM</TDNUMLEFTU>
     <TDFAMILY>HELVE</TDFAMILY>
     <TDHEIGHT>120</TDHEIGHT>
     <TDBOLD>*</TDBOLD>
     <TDITALIC>*</TDITALIC>
     <TDUNDERLIN>*</TDUNDERLIN>
     <LANGU>P</LANGU>
     <CAPTION>Resumo -  Direita</CAPTION>
    </SSFPARAS>
   </SSFPARAS>
   <STXSTAB>
    <STXSTAB>
     <ACTIVE>A</ACTIVE>
     <STYLENAME>ZFIS002</STYLENAME>
     <TDPARGRAPH>H2</TDPARGRAPH>
     <TDPOSITION>01</TDPOSITION>
     <TDTABPOS>10.0</TDTABPOS>
     <TDTABPOSU>CM</TDTABPOSU>
     <TDTJUSTIFY>LEFT</TDTJUSTIFY>
    </STXSTAB>
    <STXSTAB>
     <ACTIVE>A</ACTIVE>
     <STYLENAME>ZFIS002</STYLENAME>
     <TDPARGRAPH>H2</TDPARGRAPH>
     <TDPOSITION>02</TDPOSITION>
     <TDTABPOS>16.0</TDTABPOS>
     <TDTABPOSU>CM</TDTABPOSU>
     <TDTJUSTIFY>LEFT</TDTJUSTIFY>
    </STXSTAB>
   </STXSTAB>
  </asx:values>
 </asx:abap>
</abapGit>
