<?xml version="1.0" encoding="utf-8"?>
<abapGit version="v1.0.0" serializer="LCL_OBJECT_SUSO" serializer_version="v1.0.0">
 <asx:abap xmlns:asx="http://www.sap.com/abapxml" version="1.0">
  <asx:values>
   <TOBJ>
    <OBJCT>ZWS0004</OBJCT>
    <FIEL1>ZDM_ID_INT</FIEL1>
    <FIEL2>ZDM_ID_ACA</FIEL2>
    <OCLSS>ZSD</OCLSS>
   </TOBJ>
   <TOBJT>
    <LANGU>P</LANGU>
    <OBJECT>ZWS0004</OBJECT>
    <TTEXT>Autorização de Ação e Interface</TTEXT>
   </TOBJT>
   <TOBJVORFLG>
    <OBJCT>ZWS0004</OBJCT>
   </TOBJVORFLG>
  </asx:values>
 </asx:abap>
</abapGit>
